README.md
setup.py
empress/__init__.py
empress/_parameter_descriptions.py
empress/_plot.py
empress/_plot_utils.py
empress/citations.bib
empress/compression_utils.py
empress/core.py
empress/plugin_setup.py
empress/taxonomy_utils.py
empress/tools.py
empress/tree.py
empress.egg-info/PKG-INFO
empress.egg-info/SOURCES.txt
empress.egg-info/dependency_links.txt
empress.egg-info/entry_points.txt
empress.egg-info/requires.txt
empress.egg-info/top_level.txt
empress/scripts/__init__.py
empress/scripts/_cli.py
empress/support_files/css/empress.css
empress/support_files/js/animation-panel-handler.js
empress/support_files/js/animator.js
empress/support_files/js/barplot-layer.js
empress/support_files/js/barplot-panel-handler.js
empress/support_files/js/biom-table.js
empress/support_files/js/bp-tree.js
empress/support_files/js/byte-array.js
empress/support_files/js/camera.js
empress/support_files/js/canvas-events.js
empress/support_files/js/colorer.js
empress/support_files/js/drawer.js
empress/support_files/js/emperor-callbacks.js
empress/support_files/js/empress.js
empress/support_files/js/enable-disable-animation-tab.js
empress/support_files/js/enable-disable-side-panel-tab.js
empress/support_files/js/enable-disable-tab.js
empress/support_files/js/export-util.js
empress/support_files/js/layouts-util.js
empress/support_files/js/legend.js
empress/support_files/js/select-node-menu.js
empress/support_files/js/shearer.js
empress/support_files/js/side-panel-handler.js
empress/support_files/js/tree-controller.js
empress/support_files/js/util.js
empress/support_files/js/vector-ops.js
empress/support_files/templates/empress-template.html
empress/support_files/templates/index.html
empress/support_files/templates/side-panel.html
empress/support_files/vendor/FileSaver.min.js
empress/support_files/vendor/chroma.min.js
empress/support_files/vendor/gl-matrix.min.js
empress/support_files/vendor/jquery-2.2.4.min.js
empress/support_files/vendor/require-2.1.22.min.js
empress/support_files/vendor/spectrum.min.css
empress/support_files/vendor/spectrum.min.js
empress/support_files/vendor/toastr.min.css
empress/support_files/vendor/toastr.min.js
