Metadata-Version: 2.1
Name: empress
Version: 1.2.0
Summary: Fast and scalable phylogenetic tree viewer for multi-omic data analysis
Home-page: http://github.com/biocore/empress
Author: Empress Development Team
Author-email: kcantrel@ucsd.edu
Maintainer: Empress development team
Maintainer-email: kcantrel@ucsd.edu
License: BSD-3-Clause
Platform: UNKNOWN
Classifier: Development Status :: 5 - Production/Stable
Classifier: License :: OSI Approved :: BSD License
Classifier: Topic :: Software Development :: Libraries :: Application Frameworks
Classifier: Topic :: Software Development :: User Interfaces
Classifier: Programming Language :: Python
Classifier: Programming Language :: Python :: 3.5
Classifier: Programming Language :: Python :: 3.6
Classifier: Programming Language :: Python :: 3.7
Classifier: Programming Language :: Python :: Implementation :: CPython
Classifier: Operating System :: OS Independent
Classifier: Operating System :: POSIX
Classifier: Operating System :: MacOS :: MacOS X
Provides-Extra: test
Provides-Extra: all
